faster_api/__init__.py
faster_api/cli.py
faster_api/messages.py
faster_api/templates/__init__.py
faster_api/templates/app/__init__.py
faster_api/templates/app/crud.py
faster_api/templates/app/models.py
faster_api/templates/app/schemas.py
faster_api/templates/app/views.py
faster_api/templates/project/.env.example
faster_api/templates/project/README.md
faster_api/templates/project/alembic.ini
faster_api/templates/project/docker-compose.yml
faster_api/templates/project/pytest.ini
faster_api/templates/project/alembic/env.py
faster_api/templates/project/alembic/script.py.mako
faster_api/templates/project/alembic/versions/.gitkeep
faster_api/templates/project/app/__init__.py
faster_api/templates/project/app/main.py
faster_api/templates/project/app/auth/__init__.py
faster_api/templates/project/app/auth/crud.py
faster_api/templates/project/app/auth/exceptions.py
faster_api/templates/project/app/auth/models.py
faster_api/templates/project/app/auth/schemas.py
faster_api/templates/project/app/auth/views.py
faster_api/templates/project/app/core/__init__.py
faster_api/templates/project/app/core/config.py
faster_api/templates/project/app/core/deps.py
faster_api/templates/project/app/core/security.py
faster_api/templates/project/app/core/db/__init__.py
faster_api/templates/project/app/core/db/base.py
faster_api/templates/project/app/core/db/session.py
faster_api/templates/project/app/core/db/__pycache__/__init__.cpython-313.pyc
faster_api/templates/project/app/core/db/__pycache__/base.cpython-313.pyc
faster_api/templates/project/app/core/db/__pycache__/session.cpython-313.pyc
faster_api/templates/project/app/core/routers/__init__.py
faster_api/templates/project/app/core/routers/v1.py
faster_api/templates/project/app/core/routers/__pycache__/__init__.cpython-313.pyc
faster_api/templates/project/app/core/routers/__pycache__/v1.cpython-313.pyc
faster_api/templates/project/app/user/__init__.py
faster_api/templates/project/app/user/crud.py
tle_faster_api-0.2.3.dist-info/METADATA
tle_faster_api-0.2.3.dist-info/WHEEL
tle_faster_api-0.2.3.dist-info/entry_points.txt
tle_faster_api-0.2.3.dist-info/top_level.txt
tle_faster_api-0.2.3.dist-info/RECORD
