Metadata-Version: 2.4
Name: tle-faster-api
Version: 0.2.3
Summary: A CLI tool for bootstrapping FastAPI projects and apps
Home-page: https://github.com/tle-nate/faster-api
Author: tlenate
License: MIT
Project-URL: Source, https://github.com/tle-nate/faster-api
Project-URL: Issue Tracker, https://github.com/tle-nate/faster-api/issues
Keywords: fastapi cli scaffold generator
Classifier: Development Status :: 3 - Alpha
Classifier: Intended Audience :: Developers
Classifier: Topic :: Software Development :: Build Tools
Classifier: License :: OSI Approved :: MIT License
Classifier: Programming Language :: Python :: 3
Classifier: Operating System :: OS Independent
Requires-Python: >=3.7
Requires-Dist: fastapi
Requires-Dist: pydantic
Requires-Dist: alembic
Requires-Dist: passlib
Requires-Dist: sqlalchemy
Requires-Dist: psycopg
Requires-Dist: psycopg-binary
Requires-Dist: python-jose
Requires-Dist: python-multipart
Requires-Dist: argon2_cffi
Requires-Dist: uvicorn
Requires-Dist: rich
Requires-Dist: python-dotenv
Requires-Dist: pydantic-settings
Dynamic: author
Dynamic: classifier
Dynamic: description
Dynamic: description-content-type
Dynamic: home-page
Dynamic: keywords
Dynamic: license
Dynamic: project-url
Dynamic: requires-dist
Dynamic: requires-python
Dynamic: summary
